{"Version":"4","Charset":"UTF-8","Variables":{"cookiepre":"B7Y9_2132_","auth":null,"saltkey":"TCC400zh","member_uid":"0","member_username":"","member_avatar":"https://avatar.saraba1st.com/data/avatar/000/00/00/00_avatar_small.jpg","groupid":"7","formhash":"e87d9b17","ismoderator":"0","readaccess":"20","notice":{"newpush":"0","newpm":"0","newprompt":"0","newmypost":"0"},"thread":{"tid":"1085129","fid":"6","posttableid":"0","typeid":"18","sortid":"0","readperm":"0","price":"0","author":"黄前久美子","authorid":"407355","subject":"『響け！ユーフォニアム／吹响吧！上低音号』４月","dateline":"1419661866","lastpost":"2019-4-7 08:26","lastposter":"JustW","views":"815868","replies":"15002","displayorder":"0","highlight":"0","digest":"0","rate":"0","special":"0","attachment":"2","moderated":"0","closed":"0","stickreply":"0","recommends":"0","recommend_add":"0","recommend_sub":"0","heats":"1199","status":"32","isgroup":"0","favtimes":"222","sharetimes":"0","stamp":"-1","icon":"-1","pushedaid":"0","cover":"0","replycredit":"0","relatebytag":"0","maxposition":"15554","bgcolor":"","comments":"0","hidden":"0","threadtable":"forum_thread","threadtableid":"0","posttable":"forum_post","addviews":"9","allreplies":"15002","is_archived":"","archiveid":"0","subjectenc":"%E3%80%8E%E9%9F%BF%E3%81%91%EF%BC%81%E3%83%A6%E3%83%BC%E3%83%95%E3%82%A9%E3%83%8B%E3%82%A2%E3%83%A0%EF%BC%8F%E5%90%B9%E5%93%8D%E5%90%A7%EF%BC%81%E4%B8%8A%E4%BD%8E%E9%9F%B3%E5%8F%B7%E3%80%8F%EF%BC%94%E6%9C%88","short_subject":"『響け！ユーフォニアム／吹响吧！上低音号』４月 ...","replycredit_rule":{"extcreditstype":"5"},"recommendlevel":"0","heatlevel":"2","relay":"0","ordertype":"0","recommend":"0"},"fid":"6","postlist":[{"pid":"30955355","tid":"1085129","first":"0","author":"sandro","authorid":"31986","dateline":"2015-12-7 22:28","message":"<div class=\"reply_wrap\"><a href=\"https://bbs.saraba1st.com/2b/forum.php?mod=redirect&amp;goto=findpost&amp;pid=30954693&amp;ptid=1085129\"><font color=\"#999999\">SRT 发表于 2015-12-7 21:05</font></a><br />\r\nhttp://tieba.baidu.com/p/4201523004 <br />\r\nanimestyle 京吹特辑深度山田&amp;石原深长篇访谈翻译<br />\r\n ...</div><br />\n乐器的阴影高光反光全手绘太可怕了。。。","anonymous":"0","attachment":"0","status":"0","replycredit":"0","position":"13866","username":"sandro","adminid":"0","groupid":"54","memberstatus":"0","number":"13381","dbdateline":"1449498485","groupiconid":"13"},{"pid":"30955490","tid":"1085129","first":"0","author":"巴啦啦小兔兔儿","authorid":"431781","dateline":"2015-12-7 22:44","message":"<div class=\"img\"><img src=\"http://img.saraba1st.com/forum/201512/07/224337f2hbvtm6d7e5kgt5.jpg\" attach=\"30955490\" /></div><img src=\"https://static.saraba1st.com/image/smiley/face/116.gif\" /><font style=\"color:rgb(16, 39, 63)\"><font style=\"background-color:rgb(255, 248, 231)\">姐姐比久美子矮 然而胸比久美子大</font></font><font color=\"#10273f\"><font style=\"background-color:rgb(255, 248, 231)\"> </font></font><br />\r\n<br />\r\n<br />\r\n","anonymous":"0","attachment":"0","status":"0","replycredit":"0","position":"13867","username":"巴啦啦小兔兔儿","adminid":"0","groupid":"32","memberstatus":"0","number":"13382","dbdateline":"1449499442","attachments":[],"imagelist":[],"groupiconid":"8"},{"pid":"30955562","tid":"1085129","first":"0","author":"心之渊","authorid":"219246","dateline":"2015-12-7 22:52","message":"山田 这一集，不仅要重点表现出久美子和丽奈的心情，还有叶月失恋的故事。哪一边都必须好好的表现出来，是不能省略的。如果描写过多叶月，久美子和丽奈看起来就会很草率。也就是说，要是做的不好就会给人一种“这边人家都伤害的这么深了，你们还在这里干啥呢？”，所以非常的危险。只能把两边的心情非常非常认真的表现出来。所以长度就变长了。cut数比起其他的集数也很多<br />\n<br />\n<br />\n<img src=\"https://static.saraba1st.com/image/smiley/face/154.gif\" /><br />\n<br />\n<br />\n<font color=\"#333333\">山田 偶尔也会突然说“我喜欢泷老师”。虽然很没头没脑的，但是心情却很坚定。所以很有魅力，想被她折腾的排名第一的人</font><br />\r\n<font color=\"#333333\">小黑 想被折腾的人是，山田吗？</font><br />\r\n<font color=\"#333333\">山田 久美子啊！（笑）</font><br />\r\n<font color=\"#333333\"><br />\r\n</font><br />\r\n<img src=\"https://static.saraba1st.com/image/smiley/face/58.gif\" /><br />\r\n","anonymous":"0","attachment":"0","status":"0","replycredit":"0","position":"13868","username":"心之渊","adminid":"0","groupid":"57","memberstatus":"0","number":"13383","dbdateline":"1449499940","groupiconid":"12"},{"pid":"30955568","tid":"1085129","first":"0","author":"静肃之怀刃","authorid":"271236","dateline":"2015-12-7 22:52","message":"<div class=\"reply_wrap\"><a href=\"https://bbs.saraba1st.com/2b/forum.php?mod=redirect&amp;goto=findpost&amp;pid=30955115&amp;ptid=1085129\"><font color=\"#999999\">starring 发表于 2015-12-7 21:56</font></a><br />\r\n和服的小黄真可爱（谁来把那只猴子抓走</div><br />\n我擦，丽奈真的为小黄生猴子了？官方恶意啊！","anonymous":"0","attachment":"0","status":"0","replycredit":"0","position":"13869","username":"静肃之怀刃","adminid":"-1","groupid":"26","memberstatus":"0","number":"13384","dbdateline":"1449499961","groupiconid":"special"},{"pid":"30955578","tid":"1085129","first":"0","author":"eaglet_loki","authorid":"134856","dateline":"2015-12-7 22:54","message":"<div class=\"reply_wrap\"><a href=\"https://bbs.saraba1st.com/2b/forum.php?mod=redirect&amp;goto=findpost&amp;pid=30955490&amp;ptid=1085129\"><font color=\"#999999\">巴啦啦小兔兔儿 发表于 2015-12-7 22:44</font></a><br />\r\n姐姐比久美子矮 然而胸比久美子大</font> </font></div><br />\n远近法……","anonymous":"0","attachment":"0","status":"0","replycredit":"0","position":"13870","username":"eaglet_loki","adminid":"0","groupid":"54","memberstatus":"0","number":"13385","dbdateline":"1449500054","groupiconid":"13"},{"pid":"30955587","tid":"1085129","first":"0","author":"心之渊","authorid":"219246","dateline":"2015-12-7 22:55","message":"<div class=\"reply_wrap\">小黑 丽奈的手指碰着久美子的嘴唇这一段演出很有冲击呢。这是哪位的想法呢？<br />\r\n石原 （默默地指着山田）<br />\r\n山田 不好意思这一段描写有一点色气（笑）<br />\r\n小黑 哈哈哈哈哈（笑）<br />\r\n山田 分镜的时候觉得这样才有深夜的感觉呢。就像是在半夜写情书一样感觉非常愉快。在山上的场景久美子渐渐地看起来像是一位少年。我觉得要是看起来就像是一位夏季恋爱的少年就好了啊。这是对于久美子而言的“第一次”嘛<br />\r\n小黑 就像，初吻一样？<br />\r\n山田 这么说呢。就像是初体验一样。<br />\r\n小黑 我明白了（笑）<br />\r\n石原 不过这里又要说一下男女之间的不同了，你觉得男性能不能画出这种分镜？<br />\r\n小黑 哎呀，不行吧<br />\r\n石原 是嘛（笑）。我也觉得男性画的话估计这一段会更加猥亵一些<br />\r\n小黑 没错。这么说，感觉像是第一次看真百合一样<br />\r\n石原 没错。嘛这只是我们看起来是百合（笑）<br />\r\n山田 原来如此，不管是丽奈还是久美子的感情，我还以为难道你们对两人的关系有什么违和感吗？<br />\r\n石原 没有<br />\r\n小黑 嗯，没啥违和感<br />\r\n山田 （笑）<br />\r\n小黑 看了第8集我就觉得“所谓百合，不就是这个吗？”。和男性幻想的百合有不同呢<br />\r\n石原 嗯嗯。是的<br />\r\n小黑 我对百合漫画也不是特别了解，感觉不是那种轻松百合漫画而是面向成年人的女性向漫画的现实系作品。<br />\r\n石原 没错。不过山田偶尔也会做过头<br />\r\n山田 啊？！（笑）<br />\r\n石原 我觉得玉子市场的时候就是，非常的现实<br />\r\n小黑 诶？是吗？<br />\r\n石原 百合向的描写太过认真了<br />\r\n小黑 但是山田不认为那是百合吧<br />\r\n山田 嗯，没错<br />\r\n小黑 但是我也觉得玉子市场是百合<br />\r\n山田 啊 ~，是吗？一定是关于小绿的剧情吧<br />\r\n小黑 是啊<br />\r\n石原 没错，那个不是很认真吗（笑）<br />\r\n山田 是吗<br />\r\n石原 但是男性追求的百合。不仅仅是这个哦<br />\r\n小黑 （插话）不对不对那是因为山田小姐觉得这不是百合啊！<br />\r\n石原 （继续）男性追求的百合，是更加嘿嘿嘿的……<br />\r\n山田 （插话）你们冷静一下好吗（笑）<br />\r\n小黑 不好意思。有些兴奋了<br />\r\n三人 （笑）<br />\r\n山田 是嘛。所以说我对于明显的百合是不会描写的。我只是想描写青春期<br />\r\n小黑 在什么情况下<br />\r\n山田 基本上都是。玉子啊丽奈啊都是。我是想描写青春期！<br />\r\n小黑 想描写青春期的想法吗？<br />\r\n山田 没错。对于这些孩子的视角我很有兴趣</div><br />\n山田对青春期的执念是有多深<img src=\"https://static.saraba1st.com/image/smiley/face/92.gif\" /> <br />\r\n以及原来参考的演员是深田恭子吧<br />\r\n","anonymous":"0","attachment":"0","status":"0","replycredit":"0","position":"13871","username":"心之渊","adminid":"0","groupid":"57","memberstatus":"0","number":"13386","dbdateline":"1449500119","groupiconid":"12"},{"pid":"30955657","tid":"1085129","first":"0","author":"心之渊","authorid":"219246","dateline":"2015-12-7 23:04","message":"<div class=\"reply_wrap\"><a href=\"https://bbs.saraba1st.com/2b/forum.php?mod=redirect&amp;goto=findpost&amp;pid=30955490&amp;ptid=1085129\"><font color=\"#999999\">巴啦啦小兔兔儿 发表于 2015-12-7 22:44</font></a><br />\r\n姐姐比久美子矮 然而胸比久美子大 </div><br />\n哦呀，姐姐好可爱<br />\r\n当然我9世界第一可爱<img src=\"https://static.saraba1st.com/image/smiley/face/159.jpg\" /><br />\r<br />\r<br />\r<div class=\"reply_wrap\">小黑 明日香的角色性格，是石原还是山田的风格更多呢<br />\r\n石原 嗯，怎么说呢？<br />\r\n小黑 我是觉得石原的风格更明显<br />\r\n石原 啊，嘛。我觉得在制作上或多或少有自己的投影。要是从这个意义上说的话，确实我适合明日香。</div>花田久美子<br />\r\n石原明日香<br />\r\n也是不能好了<img src=\"https://static.saraba1st.com/image/smiley/face/149.gif\" /><br />\r\n","anonymous":"0","attachment":"0","status":"0","replycredit":"0","position":"13872","username":"心之渊","adminid":"0","groupid":"57","memberstatus":"0","number":"13387","dbdateline":"1449500687","groupiconid":"12"},{"pid":"30955709","tid":"1085129","first":"0","author":"eaglet_loki","authorid":"134856","dateline":"2015-12-7 23:12","message":"石原和采访在山田面前刹不住车了 <img src=\"https://static.saraba1st.com/image/smiley/face/20.gif\" /><br />\n<br />\n<br />\n连小绿都被否定了，看来是否是百合，只有女性有发言权啊","anonymous":"0","attachment":"0","status":"0","replycredit":"0","position":"13873","username":"eaglet_loki","adminid":"0","groupid":"54","memberstatus":"0","number":"13388","dbdateline":"1449501144","groupiconid":"13"},{"pid":"30955870","tid":"1085129","first":"0","author":"Fermata","authorid":"173457","dateline":"2015-12-7 23:33","message":"我不是百合党但我已经信了。<br />\r\n山田姐姐你玩弄我感情<img src=\"https://static.saraba1st.com/image/smiley/face/09.gif\" />","anonymous":"0","attachment":"0","status":"0","replycredit":"0","position":"13874","username":"Fermata","adminid":"-1","groupid":"4","memberstatus":"0","number":"13389","dbdateline":"1449502414","groupiconid":null},{"pid":"30955915","tid":"1085129","first":"0","author":"巴啦啦小兔兔儿","authorid":"431781","dateline":"2015-12-7 23:39","message":"<div class=\"reply_wrap\"><font color=\"#999999\">心之渊 发表于 2015-12-7 23:04</font><br />\r\n<font color=\"#999999\">哦呀，姐姐好可爱<br />\r\n当然我9世界第一可爱<br />\n<br />\n<br />\n</font></div><br />\n“明日香前辈有喜欢的人吗？” “怎么可能，我的最爱只有悠风号君一个”<br />\r\n山田：“石原桑有喜欢的人吗？”石原：“怎么可能，我的最爱都是我画出来的宽骨盆萝卜腿布鲁玛少女”","anonymous":"0","attachment":"0","status":"8","replycredit":"0","position":"13875","username":"巴啦啦小兔兔儿","adminid":"0","groupid":"32","memberstatus":"0","number":"13390","dbdateline":"1449502774","groupiconid":"8"},{"pid":"30959567","tid":"1085129","first":"0","author":"双子蜗牛","authorid":"246724","dateline":"2015-12-8 12:52","message":"山田老师你还真是要否定到底呀_(:3」∠)_","anonymous":"0","attachment":"0","status":"0","replycredit":"0","position":"13876","username":"双子蜗牛","adminid":"0","groupid":"32","memberstatus":"0","number":"13391","dbdateline":"1449550347","groupiconid":"8"},{"pid":"30959825","tid":"1085129","first":"0","author":"dxxtiger","authorid":"50655","dateline":"2015-12-8 13:23","message":"简单说就是<br />\n<br />\n<br />\n蛋市场：你们想太多了<br />\r\n京吹：你们没想太多<br />\n<br />\n<br />\n么？","anonymous":"0","attachment":"0","status":"0","replycredit":"0","position":"13877","username":"dxxtiger","adminid":"0","groupid":"57","memberstatus":"0","number":"13392","dbdateline":"1449552239","groupiconid":"12"},{"pid":"30959928","tid":"1085129","first":"0","author":"steinson","authorid":"424096","dateline":"2015-12-8 13:39","message":"为什么要虐我常盘绿，差评。","anonymous":"0","attachment":"0","status":"0","replycredit":"0","position":"13878","username":"steinson","adminid":"-1","groupid":"4","memberstatus":"0","number":"13393","dbdateline":"1449553197","groupiconid":null},{"pid":"30960118","tid":"1085129","first":"0","author":"tenjou","authorid":"236029","dateline":"2015-12-8 14:04","message":"<div class=\"reply_wrap\"><a href=\"https://bbs.saraba1st.com/2b/forum.php?mod=redirect&amp;goto=findpost&amp;pid=30955115&amp;ptid=1085129\"><font color=\"#999999\">starring 发表于 2015-12-7 21:56</font></a><br />\r\n和服的小黄真可爱（谁来把那只猴子抓走</div><br />\n诶？不是想做那只猴子吗？<img src=\"https://static.saraba1st.com/image/smiley/animal/141.gif\" /><br />\r\n","anonymous":"0","attachment":"0","status":"0","replycredit":"0","position":"13879","username":"tenjou","adminid":"0","groupid":"52","memberstatus":"0","number":"13394","dbdateline":"1449554657","groupiconid":"10"},{"pid":"30979422","tid":"1085129","first":"0","author":"结标淡希","authorid":"178337","dateline":"2015-12-10 12:08","message":"<div class=\"img\"><img src=\"http://ww2.sinaimg.cn/large/6e8b1afbgw1eyufn1n1u3j20ss15o7bi.jpg\" width=\"1036\" height=\"1500\" /></div><br />\n<br />\n<br />\n姐姐的唇彩算是扣分项了...","anonymous":"0","attachment":"0","status":"0","replycredit":"0","position":"13880","username":"结标淡希","adminid":"0","groupid":"54","memberstatus":"0","number":"13395","dbdateline":"1449720521","groupiconid":"13"},{"pid":"30980099","tid":"1085129","first":"0","author":"steinson","authorid":"424096","dateline":"2015-12-10 13:12","message":"其实剧场版拍老黄爱情故事就好了。","anonymous":"0","attachment":"0","status":"0","replycredit":"0","position":"13881","username":"steinson","adminid":"-1","groupid":"4","memberstatus":"0","number":"13396","dbdateline":"1449724365","groupiconid":null},{"pid":"30980261","tid":"1085129","first":"0","author":"文文情报屋","authorid":"180912","dateline":"2015-12-10 13:29","message":"其实现在小黄和她姐姐之间，这点微妙的小矛盾也可以做点文章的","anonymous":"0","attachment":"0","status":"0","replycredit":"0","position":"13882","username":"文文情报屋","adminid":"0","groupid":"53","memberstatus":"0","number":"13397","dbdateline":"1449725396","groupiconid":"11"},{"pid":"30980283","tid":"1085129","first":"0","author":"文文情报屋","authorid":"180912","dateline":"2015-12-10 13:32","message":"我开始怀疑山田的青春期都做了什么了……<br />\r\n山田你对青春期是不是有什么误解……？","anonymous":"0","attachment":"0","status":"0","replycredit":"0","position":"13883","username":"文文情报屋","adminid":"0","groupid":"53","memberstatus":"0","number":"13398","dbdateline":"1449725527","groupiconid":"11"},{"pid":"30980639","tid":"1085129","first":"0","author":"心之渊","authorid":"219246","dateline":"2015-12-10 14:09","message":"<div class=\"reply_wrap\"><a href=\"https://bbs.saraba1st.com/2b/forum.php?mod=redirect&amp;goto=findpost&amp;pid=30979422&amp;ptid=1085129\"><font color=\"#999999\">结标淡希 发表于 2015-12-10 12:08</font></a><br />\r\n姐姐的唇彩算是扣分项了...</div><br />\n特点鲜明<br />\r\n擦了以后这个笑容会像叶月的","anonymous":"0","attachment":"0","status":"0","replycredit":"0","position":"13884","username":"心之渊","adminid":"0","groupid":"57","memberstatus":"0","number":"13399","dbdateline":"1449727789","groupiconid":"12"},{"pid":"30980899","tid":"1085129","first":"0","author":"结标淡希","authorid":"178337","dateline":"2015-12-10 14:30","message":"<div class=\"reply_wrap\"><a href=\"https://bbs.saraba1st.com/2b/forum.php?mod=redirect&amp;goto=findpost&amp;pid=30980639&amp;ptid=1085129\"><font color=\"#999999\">心之渊 发表于 2015-12-10 14:09</font></a><br />\r\n特点鲜明<br />\r\n擦了以后这个笑容会像叶月的</div><br />\n<div class=\"img\"><img src=\"http://ww2.sinaimg.cn/large/6e8b1afbgw1eyujmym65hj20ss15ok5i.jpg\" /></div><br />\n<br />\n<br />\n仔细看看是有点...","anonymous":"0","attachment":"0","status":"0","replycredit":"0","position":"13885","username":"结标淡希","adminid":"0","groupid":"54","memberstatus":"0","number":"13400","dbdateline":"1449729007","groupiconid":"13"},{"pid":"30983316","tid":"1085129","first":"0","author":"hujingjing","authorid":"184805","dateline":"2015-12-10 18:16","message":"哈哈哈哈，石原和山田这访谈看的好有趣，所以说，有些微妙的东西还是女人创作起来比较有魔性啊，石原说的太猥琐了哈哈哈，“男性幻想的百合，可不仅仅是这样的啊”，噗<br />\n<br />\n<br />\n其实当时看第八集的时候，最棒的就是这种氛围了，安静神秘，暧昧的空气无处不在，我一个人走过挺多次夜路的，走夜路最赞的就是那种安静但是自然的声音无处不在的感觉，周围只剩下脚步和蝉叫声，还有零零散散的对话，山田也说了，仿佛像半夜写情书一样的愉快（这比喻太赞了），就好像要进行夏季恋爱一样www，其实我一点都不纠结到底是不是百合什么的，其实一点都不重要，我的心情就如同久美子一样，看到第八集这样的演出，就算这动画马上就完结也无所谓了","anonymous":"0","attachment":"0","status":"0","replycredit":"0","position":"13886","username":"hujingjing","adminid":"0","groupid":"57","memberstatus":"0","number":"13401","dbdateline":"1449742571","groupiconid":"12"},{"pid":"30984955","tid":"1085129","first":"0","author":"1号黑球","authorid":"276193","dateline":"2015-12-10 21:36","message":"别人还在玩五颜六色的头发，鋈已经在玩五彩瞳孔了","anonymous":"0","attachment":"0","status":"0","replycredit":"0","position":"13887","username":"1号黑球","adminid":"0","groupid":"57","memberstatus":"0","number":"13402","dbdateline":"1449754596","groupiconid":"12"},{"pid":"30999210","tid":"1085129","first":"0","author":"tenjou","authorid":"236029","dateline":"2015-12-11 20:03","message":"<div class=\"reply_wrap\">引用第13783楼hujingjing于2015-12-10 18:16发表的:<br />\r\n哈哈哈哈，石原和山田这访谈看的好有趣，所以说，有些微妙的东西还是女人创作起来比较有魔性啊，石原说的太......</div><br />\n和久美子的心情一样吗，久美子当时的心情可是“在此陨命也没有关系”哦<img src=\"https://static.saraba1st.com/image/smiley/face/119.gif\" /><br />\n<br />\n<br />\n----发送自 <a href=\"http://stage1.5j4m.com/?1.17\">STAGE1 App for Android.</a>","anonymous":"0","attachment":"0","status":"8","replycredit":"0","position":"13888","username":"tenjou","adminid":"0","groupid":"52","memberstatus":"0","number":"13403","dbdateline":"1449835412","groupiconid":"10"},{"pid":"30999269","tid":"1085129","first":"0","author":"lyflyflxf","authorid":"257086","dateline":"2015-12-11 20:12","message":"<div class=\"reply_wrap\"><a href=\"https://bbs.saraba1st.com/2b/forum.php?mod=redirect&amp;goto=findpost&amp;pid=30983316&amp;ptid=1085129\"><font color=\"#999999\">hujingjing 发表于 2015-12-10 18:16</font></a><br />\r\n哈哈哈哈，石原和山田这访谈看的好有趣，所以说，有些微妙的东西还是女人创作起来比较有魔性啊，石原说的太 ...</div><br />\n所以第八集之后我都无法集中注意力<img src=\"https://static.saraba1st.com/image/smiley/face/161.jpg\" />","anonymous":"0","attachment":"0","status":"0","replycredit":"0","position":"13889","username":"lyflyflxf","adminid":"0","groupid":"57","memberstatus":"0","number":"13404","dbdateline":"1449835954","groupiconid":"12"},{"pid":"30999520","tid":"1085129","first":"0","author":"表演用马甲000","authorid":"431669","dateline":"2015-12-11 20:44","message":"要是出姐片全力滋兹，最近因为种种原因喜欢上沼仓先辈了。","anonymous":"0","attachment":"0","status":"0","replycredit":"0","position":"13890","username":"表演用马甲000","adminid":"-1","groupid":"4","memberstatus":"0","number":"13405","dbdateline":"1449837851","groupiconid":null},{"pid":"31000090","tid":"1085129","first":"0","author":"心之渊","authorid":"219246","dateline":"2015-12-11 21:53","message":"京阿尼祭官方repo<br />\n<br />\n<br />\n很多熟悉的staff都露脸了<br />\n<br />\n<br />\n<a href=\"http://kyoanido-event.com/2015/sp/report/\">http://kyoanido-event.com/2015/sp/report/</a><br />\n<br />\n<br />\n官方放照片就是慷慨<br />\n<br />\n<br />\n晶子阿姨10年感觉没怎么变啊<img src=\"https://static.saraba1st.com/image/smiley/face/161.jpg\" /><br />\r\n<div class=\"img\"><img src=\"http://kyoanido-event.com/img/report/img44.jpg\" /></div><br />\n<br />\n<br />\n当然，石原依旧是个逗比<br />\n<br />\n<br />\n<div class=\"img\"><img src=\"http://kyoanido-event.com/img/report/img29.jpg\" /></div><br />\r\n","anonymous":"0","attachment":"0","status":"0","replycredit":"0","position":"13891","username":"心之渊","adminid":"0","groupid":"57","memberstatus":"0","number":"13406","dbdateline":"1449841988","groupiconid":"12"},{"pid":"31000188","tid":"1085129","first":"0","author":"紫吹兰","authorid":"385748","dateline":"2015-12-11 22:05","message":"大黄这装扮明明像部里吹大管的姐姐<br />\n<br />\n<br />\n----发送自 <a href=\"http://stage1.5j4m.com/?1.19\">samsung GT-I9508,Android 5.0.1</a>","anonymous":"0","attachment":"0","status":"8","replycredit":"0","position":"13892","username":"紫吹兰","adminid":"0","groupid":"52","memberstatus":"0","number":"13407","dbdateline":"1449842715","groupiconid":"10"},{"pid":"31000556","tid":"1085129","first":"0","author":"xsk120","authorid":"211360","dateline":"2015-12-11 22:50","message":"看到石原还是如此逗比，还是很安心的233333","anonymous":"0","attachment":"0","status":"0","replycredit":"0","position":"13893","username":"xsk120","adminid":"0","groupid":"53","memberstatus":"0","number":"13408","dbdateline":"1449845443","groupiconid":"11"},{"pid":"31000825","tid":"1085129","first":"0","author":"Fermata","authorid":"173457","dateline":"2015-12-11 23:25","message":"我突然有种冲动：政委的笑容由我来守护<img src=\"https://static.saraba1st.com/image/smiley/face/91.gif\" />","anonymous":"0","attachment":"0","status":"0","replycredit":"0","position":"13894","username":"Fermata","adminid":"-1","groupid":"4","memberstatus":"0","number":"13409","dbdateline":"1449847500","groupiconid":null},{"pid":"31001309","tid":"1085129","first":"0","author":"lyflyflxf","authorid":"257086","dateline":"2015-12-12 00:47","message":"开心就好。人生果然还是要有点希望的","anonymous":"0","attachment":"0","status":"8","replycredit":"0","position":"13895","username":"lyflyflxf","adminid":"0","groupid":"57","memberstatus":"0","number":"13410","dbdateline":"1449852466","groupiconid":"12"}],"allowpostcomment":[],"comments":[],"commentcount":[],"ppp":"30","setting_rewriterule":{"portal_topic":"topic-{name}.html","portal_article":"article-{id}-{page}.html","forum_forumdisplay":"forum-{fid}-{page}.html","forum_viewthread":"thread-{tid}-{page}-{prevpage}.html","group_group":"group-{fid}-{page}.html","home_space":"space-{user}-{value}.html","home_blog":"blog-{uid}-{blogid}.html","forum_archiver":"{action}-{value}.html","plugin":"{pluginid}-{module}.html"},"setting_rewritestatus":["portal_topic","portal_article","forum_forumdisplay","forum_viewthread","group_group","home_space","home_blog","forum_archiver","plugin"],"forum_threadpay":"","cache_custominfo_postno":["<sup>#</sup>","楼主",""],"forum":{"password":"0"}}}