{"Version":"4","Charset":"UTF-8","Variables":{"cookiepre":"B7Y9_2132_","auth":null,"saltkey":"TCC400zh","member_uid":"0","member_username":"","member_avatar":"https://avatar.saraba1st.com/data/avatar/000/00/00/00_avatar_small.jpg","groupid":"7","formhash":"e87d9b17","ismoderator":"0","readaccess":"20","notice":{"newpush":"0","newpm":"0","newprompt":"0","newmypost":"0"},"thread":{"tid":"1336553","fid":"6","posttableid":"0","typeid":"18","sortid":"0","readperm":"0","price":"0","author":"黄前久美子","authorid":"407355","subject":"『吹响吧！上低音号』专楼 剧场版上映中 3年生篇制作決定!","dateline":"1475209544","lastpost":"2020-1-20 10:46","lastposter":"Acatv","views":"1352594","replies":"20149","displayorder":"0","highlight":"0","digest":"0","rate":"0","special":"0","attachment":"2","moderated":"1","closed":"0","stickreply":"0","recommends":"0","recommend_add":"0","recommend_sub":"0","heats":"3058","status":"3104","isgroup":"0","favtimes":"316","sharetimes":"0","stamp":"-1","icon":"-1","pushedaid":"0","cover":"0","replycredit":"0","relatebytag":"0","maxposition":"20449","bgcolor":"","comments":"0","hidden":"0","threadtable":"forum_thread","threadtableid":"0","posttable":"forum_post","addviews":"23","allreplies":"20149","is_archived":"","archiveid":"0","subjectenc":"%E3%80%8E%E5%90%B9%E5%93%8D%E5%90%A7%EF%BC%81%E4%B8%8A%E4%BD%8E%E9%9F%B3%E5%8F%B7%E3%80%8F%E4%B8%93%E6%A5%BC%20%E5%89%A7%E5%9C%BA%E7%89%88%E4%B8%8A%E6%98%A0%E4%B8%AD%203%E5%B9%B4%E7%94%9F%E7%AF%87%E5%88%B6%E4%BD%9C%E6%B1%BA%E5%AE%9A%21","short_subject":"『吹响吧！上低音号』专楼 剧场版上映中 3年生篇制作決 ...","replycredit_rule":{"extcreditstype":"5"},"recommendlevel":"0","heatlevel":"3","relay":"0","ordertype":"0","recommend":"0"},"fid":"6","postlist":[{"pid":"33779044","tid":"1336553","first":"0","author":"xtwx1716","authorid":"438553","dateline":"2016-10-5 23:20","message":"丽奈这红耳朵","anonymous":"0","attachment":"0","status":"0","replycredit":"0","position":"342","username":"xtwx1716","adminid":"0","groupid":"53","memberstatus":"0","number":"331","dbdateline":"1475680859","groupiconid":"11"},{"pid":"33779045","tid":"1336553","first":"0","author":"victorws","authorid":"425070","dateline":"2016-10-5 23:21","message":"桐谷华！桐谷华！桐谷华！<br />\n<br />\n<br />\n----发送自 <a href=\"http://stage1.5j4m.com/?1.21\">STAGE1 App for Android.</a>","anonymous":"0","attachment":"0","status":"8","replycredit":"0","position":"343","username":"victorws","adminid":"0","groupid":"49","memberstatus":"0","number":"332","dbdateline":"1475680872","groupiconid":"9"},{"pid":"33779046","tid":"1336553","first":"0","author":"心之渊","authorid":"219246","dateline":"2016-10-5 23:21","message":"小天使出来啦！","anonymous":"0","attachment":"0","status":"0","replycredit":"0","position":"344","username":"心之渊","adminid":"0","groupid":"57","memberstatus":"0","number":"333","dbdateline":"1475680876","groupiconid":"12"},{"pid":"33779051","tid":"1336553","first":"0","author":"nccvividbones","authorid":"421091","dateline":"2016-10-5 23:21","message":"不行了<img src=\"https://static.saraba1st.com/image/smiley/face/34.gif\" /><img src=\"https://static.saraba1st.com/image/smiley/face/35.gif\" />","anonymous":"0","attachment":"0","status":"1032","replycredit":"0","position":"345","username":"nccvividbones","adminid":"0","groupid":"53","memberstatus":"0","number":"334","dbdateline":"1475680903","groupiconid":"11"},{"pid":"33779055","tid":"1336553","first":"0","author":"表演用马甲000","authorid":"431669","dateline":"2016-10-5 23:21","message":"好像还不是只对亲近的人这声线，对谁都是<br />\n<br />\n<br />\n难道是音监这样要求的？<br />\r\n","anonymous":"0","attachment":"0","status":"0","replycredit":"0","position":"346","username":"表演用马甲000","adminid":"-1","groupid":"4","memberstatus":"0","number":"335","dbdateline":"1475680918","groupiconid":null},{"pid":"33779063","tid":"1336553","first":"0","author":"结标淡希","authorid":"178337","dateline":"2016-10-5 23:22","message":"....这是打算搞死乐器作监么","anonymous":"0","attachment":"0","status":"0","replycredit":"0","position":"347","username":"结标淡希","adminid":"0","groupid":"54","memberstatus":"0","number":"336","dbdateline":"1475680955","groupiconid":"13"},{"pid":"33779075","tid":"1336553","first":"0","author":"musicat","authorid":"121250","dateline":"2016-10-5 23:24","message":"秀一的戏份就这样了吧<img src=\"https://static.saraba1st.com/image/smiley/face/100.gif\" />","anonymous":"0","attachment":"0","status":"0","replycredit":"0","position":"348","username":"musicat","adminid":"0","groupid":"57","memberstatus":"0","number":"337","dbdateline":"1475681041","groupiconid":"12"},{"pid":"33779076","tid":"1336553","first":"0","author":"colohot","authorid":"436202","dateline":"2016-10-5 23:24","message":"感觉故事进展的有点快","anonymous":"0","attachment":"0","status":"0","replycredit":"0","position":"349","username":"colohot","adminid":"0","groupid":"49","memberstatus":"0","number":"338","dbdateline":"1475681049","groupiconid":"9"},{"pid":"33779077","tid":"1336553","first":"0","author":"xtwx1716","authorid":"438553","dateline":"2016-10-5 23:24","message":"小黄还真是容易受精啊","anonymous":"0","attachment":"0","status":"0","replycredit":"0","position":"350","username":"xtwx1716","adminid":"0","groupid":"53","memberstatus":"0","number":"339","dbdateline":"1475681049","groupiconid":"11"},{"pid":"33779085","tid":"1336553","first":"0","author":"岛村三月","authorid":"426241","dateline":"2016-10-5 23:24","message":"感觉第一季所有崩坏场景加起来都没这第一集目前为止崩的地方多<br />\r\n&nbsp; &nbsp; —— from <a href=\"http://126.am/S1Nyan\">S1 Nyan</a> (NOKIA Lumia 1520)","anonymous":"0","attachment":"0","status":"392","replycredit":"0","position":"351","username":"岛村三月","adminid":"0","groupid":"32","memberstatus":"0","number":"340","dbdateline":"1475681087","groupiconid":"8"},{"pid":"33779103","tid":"1336553","first":"0","author":"unnilennium","authorid":"222426","dateline":"2016-10-5 23:25","message":"小黄说心里话的毛病这集出来了好几次，赞<img src=\"https://static.saraba1st.com/image/smiley/dym/148.gif\" />","anonymous":"0","attachment":"0","status":"8","replycredit":"0","position":"352","username":"unnilennium","adminid":"0","groupid":"53","memberstatus":"0","number":"341","dbdateline":"1475681156","groupiconid":"11"},{"pid":"33779110","tid":"1336553","first":"0","author":"nccvividbones","authorid":"421091","dateline":"2016-10-5 23:26","message":"肉村本色<img src=\"https://static.saraba1st.com/image/smiley/face/154.gif\" />","anonymous":"0","attachment":"0","status":"1032","replycredit":"0","position":"353","username":"nccvividbones","adminid":"0","groupid":"53","memberstatus":"0","number":"342","dbdateline":"1475681169","groupiconid":"11"},{"pid":"33779122","tid":"1336553","first":"0","author":"安广多惠子","authorid":"269367","dateline":"2016-10-5 23:27","message":"久美子内心独白的声线好像跟1季差别挺大的感觉……是我记错了吗","anonymous":"0","attachment":"0","status":"0","replycredit":"0","position":"354","username":"安广多惠子","adminid":"0","groupid":"57","memberstatus":"0","number":"343","dbdateline":"1475681236","groupiconid":"12"},{"pid":"33779140","tid":"1336553","first":"0","author":"岛村三月","authorid":"426241","dateline":"2016-10-5 23:29","message":"当初是你要分开 分开就分开~现在又要用真爱 把我换回来~<br />\r\n&nbsp; &nbsp; —— from <a href=\"http://126.am/S1Nyan\">S1 Nyan</a> (NOKIA Lumia 1520)","anonymous":"0","attachment":"0","status":"392","replycredit":"0","position":"355","username":"岛村三月","adminid":"0","groupid":"32","memberstatus":"0","number":"344","dbdateline":"1475681357","groupiconid":"8"},{"pid":"33779153","tid":"1336553","first":"0","author":"心之渊","authorid":"219246","dateline":"2016-10-5 23:30","message":"进展略快，三话干掉第二卷<img src=\"https://static.saraba1st.com/image/smiley/face/09.gif\" />","anonymous":"0","attachment":"0","status":"0","replycredit":"0","position":"356","username":"心之渊","adminid":"0","groupid":"57","memberstatus":"0","number":"345","dbdateline":"1475681413","groupiconid":"12"},{"pid":"33779154","tid":"1336553","first":"0","author":"废基","authorid":"262725","dateline":"2016-10-5 23:30","message":"第7卷还有一集未放送","anonymous":"0","attachment":"0","status":"0","replycredit":"0","position":"357","username":"废基","adminid":"-1","groupid":"4","memberstatus":"0","number":"346","dbdateline":"1475681415","groupiconid":null},{"pid":"33779157","tid":"1336553","first":"0","author":"表演用马甲000","authorid":"431669","dateline":"2016-10-5 23:30","message":"<div class=\"reply_wrap\"><a href=\"https://bbs.saraba1st.com/2b/forum.php?mod=redirect&amp;goto=findpost&amp;pid=33779122&amp;ptid=1336553\"><font color=\"#999999\">安广多惠子 发表于 2016-10-5 23:27</font></a><br />\r\n久美子内心独白的声线好像跟1季差别挺大的感觉……是我记错了吗</div><br />\n应该不是记错，黑沢的声音整体拖长了，有点不自然。","anonymous":"0","attachment":"0","status":"0","replycredit":"0","position":"358","username":"表演用马甲000","adminid":"-1","groupid":"4","memberstatus":"0","number":"347","dbdateline":"1475681419","groupiconid":null},{"pid":"33779158","tid":"1336553","first":"0","author":"qwzsea","authorid":"375351","dateline":"2016-10-5 23:30","message":"明日香是不是多你一个不多少你一个不少的样子啊<br />\r\n对于伞木来说<br />\r\n而且之前有问题<br />\r\n现在又麻烦还是维稳的好？<br />\n<br />\n<br />\n当然看到那个吹双簧管的还以为是 优子他们组团踩人了呢","anonymous":"0","attachment":"0","status":"0","replycredit":"0","position":"359","username":"qwzsea","adminid":"0","groupid":"52","memberstatus":"0","number":"348","dbdateline":"1475681419","groupiconid":"10"},{"pid":"33779164","tid":"1336553","first":"0","author":"结标淡希","authorid":"178337","dateline":"2016-10-5 23:31","message":"小天使裸足！","anonymous":"0","attachment":"0","status":"0","replycredit":"0","position":"360","username":"结标淡希","adminid":"0","groupid":"54","memberstatus":"0","number":"349","dbdateline":"1475681463","groupiconid":"13"},{"pid":"33779172","tid":"1336553","first":"0","author":"colohot","authorid":"436202","dateline":"2016-10-5 23:31","message":"小天使的脚，我忍不住了<img src=\"https://static.saraba1st.com/image/smiley/dym/148.gif\" />","anonymous":"0","attachment":"0","status":"0","replycredit":"0","position":"361","username":"colohot","adminid":"0","groupid":"49","memberstatus":"0","number":"350","dbdateline":"1475681494","groupiconid":"9"},{"pid":"33779175","tid":"1336553","first":"0","author":"岛村三月","authorid":"426241","dateline":"2016-10-5 23:31","message":"bgm是the garden of everything？？？<br />\r\n&nbsp; &nbsp; —— from <a href=\"http://126.am/S1Nyan\">S1 Nyan</a> (NOKIA Lumia 1520)","anonymous":"0","attachment":"0","status":"392","replycredit":"0","position":"362","username":"岛村三月","adminid":"0","groupid":"32","memberstatus":"0","number":"351","dbdateline":"1475681512","groupiconid":"8"},{"pid":"33779180","tid":"1336553","first":"0","author":"musicat","authorid":"121250","dateline":"2016-10-5 23:32","message":"心疼小天使啊。<br />\r\n说起来，作画比丽奈还美女","anonymous":"0","attachment":"0","status":"0","replycredit":"0","position":"363","username":"musicat","adminid":"0","groupid":"57","memberstatus":"0","number":"352","dbdateline":"1475681572","groupiconid":"12"},{"pid":"33779181","tid":"1336553","first":"0","author":"alerbe","authorid":"98754","dateline":"2016-10-5 23:33","message":"那个车窗的背景还是很厉害的，有点像实景了。","anonymous":"0","attachment":"0","status":"0","replycredit":"0","position":"364","username":"alerbe","adminid":"0","groupid":"57","memberstatus":"0","number":"353","dbdateline":"1475681583","groupiconid":"12"},{"pid":"33779183","tid":"1336553","first":"0","author":"废基","authorid":"262725","dateline":"2016-10-5 23:33","message":"京阿尼这广告太多了吧。。。","anonymous":"0","attachment":"0","status":"0","replycredit":"0","position":"365","username":"废基","adminid":"-1","groupid":"4","memberstatus":"0","number":"354","dbdateline":"1475681585","groupiconid":null},{"pid":"33779186","tid":"1336553","first":"0","author":"冷泉夜月","authorid":"182759","dateline":"2016-10-5 23:33","message":"久美子配音有点不在状态啊<br />\n<br />\n—— 来自 HUAWEI NXT-AL10, Android 6.0","anonymous":"0","attachment":"0","status":"8","replycredit":"0","position":"366","username":"冷泉夜月","adminid":"0","groupid":"53","memberstatus":"0","number":"355","dbdateline":"1475681632","groupiconid":"11"},{"pid":"33779188","tid":"1336553","first":"0","author":"心之渊","authorid":"219246","dateline":"2016-10-5 23:33","message":"word妈<br />\r\n小天使初中太可爱了吧！！！","anonymous":"0","attachment":"0","status":"0","replycredit":"0","position":"367","username":"心之渊","adminid":"0","groupid":"57","memberstatus":"0","number":"356","dbdateline":"1475681637","groupiconid":"12"},{"pid":"33779192","tid":"1336553","first":"0","author":"布里希嘉曼","authorid":"441462","dateline":"2016-10-5 23:34","message":"铠塚真是天使啊<img src=\"https://static.saraba1st.com/image/smiley/face/34.gif\" /><br />\n<br />\n<br />\n----发送自 <a href=\"http://stage1.5j4m.com/?1.21\">LGE Nexus 4,Android 5.1.1</a>","anonymous":"0","attachment":"0","status":"8","replycredit":"0","position":"369","username":"布里希嘉曼","adminid":"0","groupid":"32","memberstatus":"0","number":"357","dbdateline":"1475681660","groupiconid":"8"},{"pid":"33779195","tid":"1336553","first":"0","author":"结标淡希","authorid":"178337","dateline":"2016-10-5 23:34","message":"我打赌，小天使这裸足抱腿的姿势九成又是石原做的模特（","anonymous":"0","attachment":"0","status":"0","replycredit":"0","position":"370","username":"结标淡希","adminid":"0","groupid":"54","memberstatus":"0","number":"358","dbdateline":"1475681680","groupiconid":"13"},{"pid":"33779203","tid":"1336553","first":"0","author":"victorws","authorid":"425070","dateline":"2016-10-5 23:35","message":"才想起来原来有一小时。。。<br />\n<br />\n<br />\n----发送自 <a href=\"http://stage1.5j4m.com/?1.21\">STAGE1 App for Android.</a>","anonymous":"0","attachment":"0","status":"8","replycredit":"0","position":"371","username":"victorws","adminid":"0","groupid":"49","memberstatus":"0","number":"359","dbdateline":"1475681735","groupiconid":"9"},{"pid":"33779205","tid":"1336553","first":"0","author":"wildwind","authorid":"102297","dateline":"2016-10-5 23:35","message":"软色情专家你京","anonymous":"0","attachment":"0","status":"0","replycredit":"0","position":"372","username":"wildwind","adminid":"0","groupid":"32","memberstatus":"0","number":"360","dbdateline":"1475681746","groupiconid":"8"}],"allowpostcomment":[],"comments":[],"commentcount":[],"ppp":"30","setting_rewriterule":{"portal_topic":"topic-{name}.html","portal_article":"article-{id}-{page}.html","forum_forumdisplay":"forum-{fid}-{page}.html","forum_viewthread":"thread-{tid}-{page}-{prevpage}.html","group_group":"group-{fid}-{page}.html","home_space":"space-{user}-{value}.html","home_blog":"blog-{uid}-{blogid}.html","forum_archiver":"{action}-{value}.html","plugin":"{pluginid}-{module}.html"},"setting_rewritestatus":["portal_topic","portal_article","forum_forumdisplay","forum_viewthread","group_group","home_space","home_blog","forum_archiver","plugin"],"forum_threadpay":"","cache_custominfo_postno":["<sup>#</sup>","楼主",""],"forum":{"password":"0"}}}