{"Version":"4","Charset":"UTF-8","Variables":{"cookiepre":"B7Y9_2132_","auth":null,"saltkey":"TCC400zh","member_uid":"0","member_username":"","member_avatar":"https://avatar.saraba1st.com/data/avatar/000/00/00/00_avatar_small.jpg","groupid":"7","formhash":"e87d9b17","ismoderator":"0","readaccess":"20","notice":{"newpush":"0","newpm":"0","newprompt":"0","newmypost":"0"},"thread":{"tid":"1336553","fid":"6","posttableid":"0","typeid":"18","sortid":"0","readperm":"0","price":"0","author":"黄前久美子","authorid":"407355","subject":"『吹响吧！上低音号』专楼 剧场版上映中 3年生篇制作決定!","dateline":"1475209544","lastpost":"2020-1-20 10:46","lastposter":"Acatv","views":"1352665","replies":"20149","displayorder":"0","highlight":"0","digest":"0","rate":"0","special":"0","attachment":"2","moderated":"1","closed":"0","stickreply":"0","recommends":"0","recommend_add":"0","recommend_sub":"0","heats":"3058","status":"3104","isgroup":"0","favtimes":"316","sharetimes":"0","stamp":"-1","icon":"-1","pushedaid":"0","cover":"0","replycredit":"0","relatebytag":"0","maxposition":"20449","bgcolor":"","comments":"0","hidden":"0","threadtable":"forum_thread","threadtableid":"0","posttable":"forum_post","addviews":"93","allreplies":"20149","is_archived":"","archiveid":"0","subjectenc":"%E3%80%8E%E5%90%B9%E5%93%8D%E5%90%A7%EF%BC%81%E4%B8%8A%E4%BD%8E%E9%9F%B3%E5%8F%B7%E3%80%8F%E4%B8%93%E6%A5%BC%20%E5%89%A7%E5%9C%BA%E7%89%88%E4%B8%8A%E6%98%A0%E4%B8%AD%203%E5%B9%B4%E7%94%9F%E7%AF%87%E5%88%B6%E4%BD%9C%E6%B1%BA%E5%AE%9A%21","short_subject":"『吹响吧！上低音号』专楼 剧场版上映中 3年生篇制作決 ...","replycredit_rule":{"extcreditstype":"5"},"recommendlevel":"0","heatlevel":"3","relay":"0","ordertype":"0","recommend":"0"},"fid":"6","postlist":[{"pid":"34133946","tid":"1336553","first":"0","author":"osore","authorid":"184969","dateline":"2016-11-10 15:46","message":"<div class=\"reply_wrap\"><a href=\"https://bbs.saraba1st.com/2b/forum.php?mod=redirect&amp;goto=findpost&amp;pid=34133878&amp;ptid=1336553\"><font color=\"#999999\">steinstein 发表于 2016-11-10 15:38</font></a><br />\r\n说实话，安编制来说一把悠风一样可以的，所以归根到底是久久水平不行。</div><br />\n精神领袖不在了啊<br />\r\n就好像皇帝没了，人心就乱了","anonymous":"0","attachment":"0","status":"0","replycredit":"0","position":"4611","username":"osore","adminid":"0","groupid":"54","memberstatus":"0","number":"4411","dbdateline":"1478763978","groupiconid":"13"},{"pid":"34134000","tid":"1336553","first":"0","author":"表演用马甲000","authorid":"431669","dateline":"2016-11-10 15:52","message":"<div class=\"reply_wrap\"><a href=\"https://bbs.saraba1st.com/2b/forum.php?mod=redirect&amp;goto=findpost&amp;pid=34133233&amp;ptid=1336553\"><font color=\"#999999\">eaglet_loki 发表于 2016-11-10 14:32</font></a><br />\r\n原作里还有一次登场只是为传递并强化一个概念，“明日香也只是一个一般的人”。我觉得这段不会有了。<br />\n<br />\n<br />\n原 ...</div><br />\n花田搞什么，这么重要的内容都能删","anonymous":"0","attachment":"0","status":"0","replycredit":"0","position":"4612","username":"表演用马甲000","adminid":"-1","groupid":"4","memberstatus":"0","number":"4412","dbdateline":"1478764335","groupiconid":null},{"pid":"34134182","tid":"1336553","first":"0","author":"钢琴猫","authorid":"459967","dateline":"2016-11-10 16:12","message":"<div class=\"reply_wrap\"><a href=\"https://bbs.saraba1st.com/2b/forum.php?mod=redirect&amp;goto=findpost&amp;pid=34133813&amp;ptid=1336553\"><font color=\"#999999\">xwr 发表于 2016-11-10 15:32</font></a><br />\r\n学园祭的众人</div><br />\n<img src=\"https://static.saraba1st.com/image/smiley/face/145.gif\" />","anonymous":"0","attachment":"0","status":"0","replycredit":"0","position":"4613","username":"钢琴猫","adminid":"0","groupid":"31","memberstatus":"0","number":"4413","dbdateline":"1478765550","groupiconid":"7"},{"pid":"34134240","tid":"1336553","first":"0","author":"xwr","authorid":"179647","dateline":"2016-11-10 16:18","message":"<div class=\"reply_wrap\"><a href=\"https://bbs.saraba1st.com/2b/forum.php?mod=redirect&amp;goto=findpost&amp;pid=34133843&amp;ptid=1336553\"><font color=\"#999999\">eaglet_loki 发表于 2016-11-10 15:35</font></a><br />\r\n拖出去砍了！<br />\r\n现在京吹2到公共路线的时候，我脑内就会响起秒5主题曲的高潮部分……</div><br />\n说真的, 我好喜欢你这个反应，在4chan看到这个图后就想看你会有什么反应。<br />\n<br />\n<br />\n秒五我大概看过接近20遍吧，那种事过境迁，物是人非的无力感某种意义上让人欲罢不能。<br />\n<br />\n<br />\n斋藤葵这个人物其实要写的话应该能扩展很多，毕竟是和三香一样是元老，退部事件要是没有这几个人在吹奏部恐怕早就土崩瓦解了，结果退部之后就变成了被人遗忘的角色，真是令人叹息。","anonymous":"0","attachment":"0","status":"0","replycredit":"0","position":"4614","username":"xwr","adminid":"0","groupid":"57","memberstatus":"0","number":"4414","dbdateline":"1478765912","groupiconid":"12"},{"pid":"34134356","tid":"1336553","first":"0","author":"xwr","authorid":"179647","dateline":"2016-11-10 16:31","message":"<div class=\"reply_wrap\"><a href=\"https://bbs.saraba1st.com/2b/forum.php?mod=redirect&amp;goto=findpost&amp;pid=34133923&amp;ptid=1336553\"><font color=\"#999999\">MikiyaKokutou 发表于 2016-11-10 15:43</font></a><br />\r\n刚想说好图收了，看到最后一张</div><br />\n其实学园祭哪怕给个葵听演奏的特写就好了，堂堂吹奏部元老，与三香等人一同度过退部事件，结果学园祭连个人影都不见，算是真的被花田遗忘了，放上此图怀念其为吹奏部作出的不朽贡献。","anonymous":"0","attachment":"0","status":"0","replycredit":"0","position":"4615","username":"xwr","adminid":"0","groupid":"57","memberstatus":"0","number":"4415","dbdateline":"1478766707","groupiconid":"12"},{"pid":"34134358","tid":"1336553","first":"0","author":"大厨麦当牛","authorid":"264923","dateline":"2016-11-10 16:31","message":"<div class=\"reply_wrap\"><font color=\"#999999\">T80UD 发表于 2016-11-10 11:47</font><br />\r\n<font color=\"#999999\">话说香织女神为什么要去穿布偶装，真是软妹的话拿来当招牌更吸引人气，搞工作分配的人是傻逼吗？ ...</font></div><br />\n分配的人应该是她自己，因为穿这种厚重闷热的布偶装最辛苦的缘故吧？","anonymous":"0","attachment":"0","status":"8","replycredit":"0","position":"4616","username":"大厨麦当牛","adminid":"0","groupid":"53","memberstatus":"0","number":"4416","dbdateline":"1478766718","groupiconid":"11"},{"pid":"34134394","tid":"1336553","first":"0","author":"xwr","authorid":"179647","dateline":"2016-11-10 16:35","message":"<div class=\"reply_wrap\"><a href=\"https://bbs.saraba1st.com/2b/forum.php?mod=redirect&amp;goto=findpost&amp;pid=34134358&amp;ptid=1336553\"><font color=\"#999999\">大厨麦当牛 发表于 2016-11-10 16:31</font></a><br />\r\n分配的人应该是她自己，因为穿这种厚重闷热的布偶装最辛苦的缘故吧？</div><br />\n突然想到，如果很热的话，会不会只穿内衣，或者全裸？","anonymous":"0","attachment":"0","status":"0","replycredit":"0","position":"4617","username":"xwr","adminid":"0","groupid":"57","memberstatus":"0","number":"4417","dbdateline":"1478766925","groupiconid":"12"},{"pid":"34134502","tid":"1336553","first":"0","author":"大厨麦当牛","authorid":"264923","dateline":"2016-11-10 16:44","message":"<div class=\"reply_wrap\"><font color=\"#999999\">xwr 发表于 2016-11-10 16:35</font><br />\r\n<font color=\"#999999\">突然想到，如果很热的话，会不会只穿内衣，或者全裸？</font></div><br />\n那种布偶内层也很脏的吧，你看她头发都罩上了，除非想得病才会那么穿。","anonymous":"0","attachment":"0","status":"8","replycredit":"0","position":"4618","username":"大厨麦当牛","adminid":"0","groupid":"53","memberstatus":"0","number":"4418","dbdateline":"1478767464","groupiconid":"11"},{"pid":"34134549","tid":"1336553","first":"0","author":"xwr","authorid":"179647","dateline":"2016-11-10 16:48","message":"<div class=\"reply_wrap\"><a href=\"https://bbs.saraba1st.com/2b/forum.php?mod=redirect&amp;goto=findpost&amp;pid=34134502&amp;ptid=1336553\"><font color=\"#999999\">大厨麦当牛 发表于 2016-11-10 16:44</font></a><br />\r\n那种布偶内层也很脏的吧，你看她头发都罩上了，除非想得病才会那么穿。 ...</div><br />\n有道理。不论外表还是内心，香织真不愧为吹奏部的女神。","anonymous":"0","attachment":"0","status":"0","replycredit":"0","position":"4619","username":"xwr","adminid":"0","groupid":"57","memberstatus":"0","number":"4419","dbdateline":"1478767731","groupiconid":"12"},{"pid":"34134569","tid":"1336553","first":"0","author":"osore","authorid":"184969","dateline":"2016-11-10 16:50","message":"<div class=\"reply_wrap\"><a href=\"https://bbs.saraba1st.com/2b/forum.php?mod=redirect&amp;goto=findpost&amp;pid=34134356&amp;ptid=1336553\"><font color=\"#999999\">xwr 发表于 2016-11-10 16:31</font></a><br />\r\n其实学园祭哪怕给个葵听演奏的特写就好了，堂堂吹奏部元老，与三香等人一同度过退部事件，结果学园祭连个 ...</div><br />\n狡兔死走狗烹不是很正常吗","anonymous":"0","attachment":"0","status":"0","replycredit":"0","position":"4621","username":"osore","adminid":"0","groupid":"54","memberstatus":"0","number":"4420","dbdateline":"1478767820","groupiconid":"13"},{"pid":"34134811","tid":"1336553","first":"0","author":"1899milan","authorid":"207642","dateline":"2016-11-10 17:12","message":"女仆装的夏纪学姐<img src=\"https://static.saraba1st.com/image/smiley/dym/154.gif\" />项圈真是太色情了<img src=\"https://static.saraba1st.com/image/smiley/dym/154.gif\" /><br />\n<br />\n<br />\n过场的后颈<img src=\"https://static.saraba1st.com/image/smiley/dym/148.gif\" />staff很懂马尾","anonymous":"0","attachment":"0","status":"0","replycredit":"0","position":"4622","username":"1899milan","adminid":"-1","groupid":"26","memberstatus":"0","number":"4421","dbdateline":"1478769136","groupiconid":"special"},{"pid":"34134847","tid":"1336553","first":"0","author":"xwr","authorid":"179647","dateline":"2016-11-10 17:15","message":"这一话OP有颜色了，那为什么之前是黑白的？","anonymous":"0","attachment":"0","status":"0","replycredit":"0","position":"4623","username":"xwr","adminid":"0","groupid":"57","memberstatus":"0","number":"4422","dbdateline":"1478769343","groupiconid":"12"},{"pid":"34134928","tid":"1336553","first":"0","author":"钢琴猫","authorid":"459967","dateline":"2016-11-10 17:22","message":"<div class=\"reply_wrap\"><a href=\"https://bbs.saraba1st.com/2b/forum.php?mod=redirect&amp;goto=findpost&amp;pid=34134847&amp;ptid=1336553\"><font color=\"#999999\">xwr 发表于 2016-11-10 17:15</font></a><br />\r\n这一话OP有颜色了，那为什么之前是黑白的？</div><br />\n等下原来不是因为我的色盲好了吗<img src=\"https://static.saraba1st.com/image/smiley/face/108.gif\" />","anonymous":"0","attachment":"0","status":"0","replycredit":"0","position":"4624","username":"钢琴猫","adminid":"0","groupid":"31","memberstatus":"0","number":"4423","dbdateline":"1478769725","groupiconid":"7"},{"pid":"34135076","tid":"1336553","first":"0","author":"jellyfis","authorid":"261623","dateline":"2016-11-10 17:34","message":"<div class=\"reply_wrap\"><font color=\"#999999\">大厨麦当牛 发表于 2016-11-10 16:31</font><br />\r\n<font color=\"#999999\">分配的人应该是她自己，因为穿这种厚重闷热的布偶装最辛苦的缘故吧？</font></div><br />\n真是麻吉天使","anonymous":"0","attachment":"0","status":"8","replycredit":"0","position":"4625","username":"jellyfis","adminid":"0","groupid":"53","memberstatus":"0","number":"4424","dbdateline":"1478770498","groupiconid":"11"},{"pid":"34135112","tid":"1336553","first":"0","author":"钢琴猫","authorid":"459967","dateline":"2016-11-10 17:38","message":"想了一下，如果不是staff玩，硬要找点意义的话……<br />\r\n颜色变化是关西大赛前后<br />\r\n黑白让我第一个想起的是op里的被风吹翻页的谱子。五线谱是黑白的。<br />\r\n演奏画面里谱子被彩笔涂满了祝福，还有贴上了彩色照片。所以这一话开始用彩色的op画面。<br />\r\n----<br />\r\n但是到这里还是staff在玩啊，好像还差一步。<br />\r\n----<br />\r\n其实是みぞれ老公回来了，世界又重新变回缤纷多彩<img src=\"https://static.saraba1st.com/image/smiley/face/119.gif\" />","anonymous":"0","attachment":"0","status":"0","replycredit":"0","position":"4626","username":"钢琴猫","adminid":"0","groupid":"31","memberstatus":"0","number":"4425","dbdateline":"1478770685","groupiconid":"7"},{"pid":"34135164","tid":"1336553","first":"0","author":"eaglet_loki","authorid":"134856","dateline":"2016-11-10 17:44","message":"OP换个颜色没大意思，像ED那样换掉几个画面，突出新章节里的主要人物才有诚意，不过新章节看来也没几个主要人物……","anonymous":"0","attachment":"0","status":"0","replycredit":"0","position":"4627","username":"eaglet_loki","adminid":"0","groupid":"54","memberstatus":"0","number":"4426","dbdateline":"1478771084","groupiconid":"13"},{"pid":"34135175","tid":"1336553","first":"0","author":"钢琴猫","authorid":"459967","dateline":"2016-11-10 17:46","message":"<div class=\"reply_wrap\"><a href=\"https://bbs.saraba1st.com/2b/forum.php?mod=redirect&amp;goto=findpost&amp;pid=34135164&amp;ptid=1336553\"><font color=\"#999999\">eaglet_loki 发表于 2016-11-10 17:44</font></a><br />\r\nOP换个颜色没大意思，像ED那样换掉几个画面，突出新章节里的主要人物才有诚意，不过新章节看来也没几个主要 ...</div><br />\n这样下去可能会变成“不做ED2没有意思”的<img src=\"https://static.saraba1st.com/image/smiley/face/145.gif\" />","anonymous":"0","attachment":"0","status":"0","replycredit":"0","position":"4628","username":"钢琴猫","adminid":"0","groupid":"31","memberstatus":"0","number":"4427","dbdateline":"1478771168","groupiconid":"7"},{"pid":"34135206","tid":"1336553","first":"0","author":"表演用马甲000","authorid":"431669","dateline":"2016-11-10 17:48","message":"看了这一话<br />\n<br />\n<br />\n黄前姐妹吵架那一段气氛没渲染好，上一个镜头还在床上滚来滚去下一个镜头连轻快的BGM都没换就直接切入严肃场境，小黄前好不容易发次火给弄得这么不给力。<br />\r\n还有有人也提到了，最后那里川岛只和黄前高坂打招呼，完全不理铠冢，这怎么想都是制作失误<br />\n<br />\n<br />\n别的地方还不错","anonymous":"0","attachment":"0","status":"0","replycredit":"0","position":"4629","username":"表演用马甲000","adminid":"-1","groupid":"4","memberstatus":"0","number":"4428","dbdateline":"1478771323","groupiconid":null},{"pid":"34135655","tid":"1336553","first":"0","author":"osore","authorid":"184969","dateline":"2016-11-10 18:37","message":"小绿干嘛不拉提琴改弹贝斯了","anonymous":"0","attachment":"0","status":"0","replycredit":"0","position":"4630","username":"osore","adminid":"0","groupid":"54","memberstatus":"0","number":"4429","dbdateline":"1478774221","groupiconid":"13"},{"pid":"34135673","tid":"1336553","first":"0","author":"osore","authorid":"184969","dateline":"2016-11-10 18:38","message":"黑白变彩色很好理解啊<br />\r\n就好像寒窗X年，整天做题生活都是灰色的，一朝金榜题名就变彩色了<img src=\"https://static.saraba1st.com/image/smiley/face/91.gif\" />","anonymous":"0","attachment":"0","status":"0","replycredit":"0","position":"4631","username":"osore","adminid":"0","groupid":"54","memberstatus":"0","number":"4430","dbdateline":"1478774337","groupiconid":"13"},{"pid":"34135734","tid":"1336553","first":"0","author":"leystage","authorid":"199900","dateline":"2016-11-10 18:45","message":"说句题外话，老师雨天开车的场景感觉是左舵车啊，作画错误？","anonymous":"0","attachment":"0","status":"8","replycredit":"0","position":"4632","username":"leystage","adminid":"0","groupid":"53","memberstatus":"0","number":"4431","dbdateline":"1478774750","groupiconid":"11"},{"pid":"34135766","tid":"1336553","first":"0","author":"巴啦啦小兔兔儿","authorid":"431781","dateline":"2016-11-10 18:49","message":"<div class=\"reply_wrap\"><a href=\"https://bbs.saraba1st.com/2b/forum.php?mod=redirect&amp;goto=findpost&amp;pid=34135734&amp;ptid=1336553\"><font color=\"#999999\">leystage 发表于 2016-11-10 18:45</font></a><br />\r\n说句题外话，老师雨天开车的场景感觉是左舵车啊，作画错误？</div><br />\n没错，考据党指出这车就是法国的进口左舵车，七几年的一款老爷车<img src=\"https://static.saraba1st.com/image/smiley/face/130.gif\" />","anonymous":"0","attachment":"0","status":"0","replycredit":"0","position":"4633","username":"巴啦啦小兔兔儿","adminid":"0","groupid":"32","memberstatus":"0","number":"4432","dbdateline":"1478774969","groupiconid":"8"},{"pid":"34135831","tid":"1336553","first":"0","author":"private","authorid":"400664","dateline":"2016-11-10 18:57","message":"<div class=\"reply_wrap\"><a href=\"https://bbs.saraba1st.com/2b/forum.php?mod=redirect&amp;goto=findpost&amp;pid=34135206&amp;ptid=1336553\"><font color=\"#999999\">表演用马甲000 发表于 2016-11-10 17:48</font></a><br />\r\n看了这一话<br />\n<br />\n<br />\n黄前姐妹吵架那一段气氛没渲染好，上一个镜头还在床上滚来滚去下一个镜头连轻快的BGM都没换就 ...</div><br />\n最后那里川岛只和黄前高坂打招呼，完全不理铠冢，这怎么想都是制作失误、<br />\r\n这一段，确实是加上去给双簧管刷镜头用的嫌疑<br />\r\n但是换一个角度，在魔法少女小圆里面，小圆带着QB去上学，都不用开口的，几个魔法少女都能直接心灵对话，但是为了掩人耳目还是要做一些早上的招呼对话<br />\r\n吹奏部天王里面说不定就有和QB契约过的<br />\r\n可能身为魔法少女的小绿和双簧管早就连上了线，在聊得欢<br />\r\n晚上还要一起去狩猎魔女<br />\r\n这个时候的中川学姐应该是个普通人在当她们的跟班吧<br />\r\n<br />\r\n<br />\r\n","anonymous":"0","attachment":"0","status":"0","replycredit":"0","position":"4634","username":"private","adminid":"-1","groupid":"4","memberstatus":"0","number":"4433","dbdateline":"1478775433","groupiconid":null},{"pid":"34135863","tid":"1336553","first":"0","author":"ziyemao0","authorid":"431791","dateline":"2016-11-10 19:01","message":"<div class=\"reply_wrap\"><a href=\"https://bbs.saraba1st.com/2b/forum.php?mod=redirect&amp;goto=findpost&amp;pid=34135831&amp;ptid=1336553\"><font color=\"#999999\">private 发表于 2016-11-10 18:57</font></a><br />\r\n最后那里川岛只和黄前高坂打招呼，完全不理铠冢，这怎么想都是制作失误、<br />\r\n这一段，确实市加上去给双簧管 ...</div><br />\n小绿根本没和小天使说过话吧？","anonymous":"0","attachment":"0","status":"0","replycredit":"0","position":"4635","username":"ziyemao0","adminid":"0","groupid":"31","memberstatus":"0","number":"4434","dbdateline":"1478775681","groupiconid":"7"},{"pid":"34135927","tid":"1336553","first":"0","author":"private","authorid":"400664","dateline":"2016-11-10 19:08","message":"<div class=\"reply_wrap\"><a href=\"https://bbs.saraba1st.com/2b/forum.php?mod=redirect&amp;goto=findpost&amp;pid=34135863&amp;ptid=1336553\"><font color=\"#999999\">ziyemao0 发表于 2016-11-10 19:01</font></a><br />\r\n小绿根本没和小天使说过话吧？</div><br />\n{之前回复市打字一半发出来了）<br />\r\n确实，可以点个头，之类的招呼让人自行想象<br />\r\n但是同为吹奏部天王，她们之间说不认识，没搭话 故事味道就淡很多了<br />\n<br />\n<br />\n换一个角度，在魔法少女小圆里面，小圆带着QB去上学，都不用开口的，几个魔法少女都能直接心灵对话，但是为了掩人耳目还是要做一些早上的招呼对话<br />\r\n说不定身为魔法少女的小绿和双簧管早就连上了线，在聊得欢<br />\r\n晚上还要一起去狩猎魔女<br />\r\n这个时候的中川学姐应该还是她们的跟班<br />\r\n","anonymous":"0","attachment":"0","status":"0","replycredit":"0","position":"4636","username":"private","adminid":"-1","groupid":"4","memberstatus":"0","number":"4435","dbdateline":"1478776115","groupiconid":null},{"pid":"34135948","tid":"1336553","first":"0","author":"leystage","authorid":"199900","dateline":"2016-11-10 19:11","message":"<div class=\"reply_wrap\"><font color=\"#999999\">巴啦啦小兔兔儿 发表于 2016-11-10 18:49</font><br />\r\n<font color=\"#999999\">没错，考据党指出这车就是法国的进口左舵车，七几年的一款老爷车</font></div><br />\n原来如此…<br />\n<br />\n<br />\n等等，日本路上可以开左舵车？！","anonymous":"0","attachment":"0","status":"8","replycredit":"0","position":"4637","username":"leystage","adminid":"0","groupid":"53","memberstatus":"0","number":"4436","dbdateline":"1478776284","groupiconid":"11"},{"pid":"34136142","tid":"1336553","first":"0","author":"private","authorid":"400664","dateline":"2016-11-10 19:34","message":"<div class=\"img\"><img src=\"http://ww3.sinaimg.cn/large/0060lm7Tgw1fal1hxpg8yj30g4092glw.jpg\" width=\"580\" height=\"326\" /></div><br />\r\n<br />\r\n<br />\r\n水调歌头.重上大吉山<br />\n<br />\n<br />\n&nbsp; &nbsp;--------丽奈<br />\r\n<br />\r\n<br />\r\n久有凌云志，重上大吉山。千里来寻故地，旧貌变新颜。到处莺歌燕舞，更有潺潺流水，高路入云端。过了北宇治，险处不须看。<br />\n<br />\n<br />\n风雷动，旌旗奋，是人寰。多少时间过去，弹指一挥间。可上大赛夺金，可下部内SOLO，谈笑凯歌还。世上无难事，只要肯登攀","anonymous":"0","attachment":"0","status":"0","replycredit":"0","position":"4638","username":"private","adminid":"-1","groupid":"4","memberstatus":"0","number":"4437","dbdateline":"1478777676","groupiconid":null},{"pid":"34136153","tid":"1336553","first":"0","author":"private","authorid":"400664","dateline":"2016-11-10 19:36","message":"一直开这个玩笑，要真的丽奈和久美子在重上大吉山的话（我好像已经被剧透过了），我想这样脑补，还要加上毛体字<img src=\"https://static.saraba1st.com/image/smiley/animal/146.gif\" /><br />\r\n草草弄了一下，还是词语有些违和","anonymous":"0","attachment":"0","status":"0","replycredit":"0","position":"4639","username":"private","adminid":"-1","groupid":"4","memberstatus":"0","number":"4438","dbdateline":"1478777770","groupiconid":null},{"pid":"34136219","tid":"1336553","first":"0","author":"钢琴猫","authorid":"459967","dateline":"2016-11-10 19:44","message":"<div class=\"reply_wrap\"><a href=\"https://bbs.saraba1st.com/2b/forum.php?mod=redirect&amp;goto=findpost&amp;pid=34136142&amp;ptid=1336553\"><font color=\"#999999\">private 发表于 2016-11-10 19:34</font></a><br />\r\n水调歌头.重上大吉山<br />\n<br />\n<br />\n&nbsp; &nbsp;--------丽奈</div><br />\n<img src=\"https://static.saraba1st.com/image/smiley/face/149.gif\" />百度图床？","anonymous":"0","attachment":"0","status":"0","replycredit":"0","position":"4640","username":"钢琴猫","adminid":"0","groupid":"31","memberstatus":"0","number":"4439","dbdateline":"1478778268","groupiconid":"7"},{"pid":"34136245","tid":"1336553","first":"0","author":"private","authorid":"400664","dateline":"2016-11-10 19:46","message":"<div class=\"reply_wrap\"><a href=\"https://bbs.saraba1st.com/2b/forum.php?mod=redirect&amp;goto=findpost&amp;pid=34136219&amp;ptid=1336553\"><font color=\"#999999\">钢琴猫 发表于 2016-11-10 19:44</font></a><br />\r\n百度图床？</div><br />\n应该不是","anonymous":"0","attachment":"0","status":"0","replycredit":"0","position":"4641","username":"private","adminid":"-1","groupid":"4","memberstatus":"0","number":"4440","dbdateline":"1478778405","groupiconid":null}],"allowpostcomment":[],"comments":[],"commentcount":[],"ppp":"30","setting_rewriterule":{"portal_topic":"topic-{name}.html","portal_article":"article-{id}-{page}.html","forum_forumdisplay":"forum-{fid}-{page}.html","forum_viewthread":"thread-{tid}-{page}-{prevpage}.html","group_group":"group-{fid}-{page}.html","home_space":"space-{user}-{value}.html","home_blog":"blog-{uid}-{blogid}.html","forum_archiver":"{action}-{value}.html","plugin":"{pluginid}-{module}.html"},"setting_rewritestatus":["portal_topic","portal_article","forum_forumdisplay","forum_viewthread","group_group","home_space","home_blog","forum_archiver","plugin"],"forum_threadpay":"","cache_custominfo_postno":["<sup>#</sup>","楼主",""],"forum":{"password":"0"}}}